reqdb/__init__.py
reqdb/api.py
reqdb/models.py
reqdb-0.12.0.dist-info/METADATA
reqdb-0.12.0.dist-info/WHEEL
reqdb-0.12.0.dist-info/licenses/LICENSE
reqdb-0.12.0.dist-info/RECORD
