Metadata-Version: 2.4
Name: reqdb
Version: 0.12.0
Summary: Python API client for ReqDB
License-File: LICENSE
Author: dcfSec
Author-email: contributor@dcfsec.com
Requires-Python: >=3.10,<4.0
Classifier: Programming Language :: Python :: 3
Classifier: Programming Language :: Python :: 3.10
Classifier: Programming Language :: Python :: 3.11
Classifier: Programming Language :: Python :: 3.12
Classifier: Programming Language :: Python :: 3.13
Classifier: Programming Language :: Python :: 3.14
Requires-Dist: authlib (>=1.4.0,<2.0.0)
Requires-Dist: joserfc (>=1.3.4,<2.0.0)
Requires-Dist: pydantic (>=2.11.4,<3.0.0)
Requires-Dist: requests (>=2.32.2,<3.0.0)
